gattfuzz/GATTFuzz.py
gattfuzz/GattFuzz.py
gattfuzz/__init__.py
gattfuzz/lib/BLECon.py
gattfuzz/lib/BLEControl.py
gattfuzz/lib/BTLog.py
gattfuzz/lib/Logger.py
gattfuzz/lib/PcapProcessor.py
gattfuzz/lib/StringMutator.py
gattfuzz/lib/ValueLCS.py
gattfuzz/lib/__init__.py
gattfuzz-0.0.14.dist-info/METADATA
gattfuzz-0.0.14.dist-info/WHEEL
gattfuzz-0.0.14.dist-info/entry_points.txt
gattfuzz-0.0.14.dist-info/top_level.txt
gattfuzz-0.0.14.dist-info/RECORD
