Metadata-Version: 2.1
Name: gattfuzz
Version: 0.0.14
Summary: A tool for fuzzing BLE GATT
Home-page: UNKNOWN
License: UNKNOWN
Platform: UNKNOWN
Requires-Python: >=3.6
Requires-Dist: bluepy (==1.3.0)
Requires-Dist: scapy (==2.4.5)
